onedep_deposition/__init__.py
onedep_deposition/decorators.py
onedep_deposition/deposit_api.py
onedep_deposition/enum.py
onedep_deposition/exceptions.py
onedep_deposition/models.py
onedep_deposition/rest_adapter.py
onedep_deposition/cli/__init__.py
onedep_deposition/cli/cli.py
onedep_deposition-0.2.dist-info/LICENSE
onedep_deposition-0.2.dist-info/METADATA
onedep_deposition-0.2.dist-info/WHEEL
onedep_deposition-0.2.dist-info/entry_points.txt
onedep_deposition-0.2.dist-info/top_level.txt
onedep_deposition-0.2.dist-info/RECORD
