Metadata-Version: 2.1
Name: onedep_deposition
Version: 0.2
Summary: Package for wrapping the OneDep deposition API services
Author-email: Neli Jose da Fonseca Junior <neli@ebi.ac.uk>
License: apache-2.0
Classifier: Development Status :: 3 - Alpha
Classifier: Programming Language :: Python :: 3
Classifier: Intended Audience :: Developers
Classifier: Natural Language :: English
Classifier: License :: OSI Approved :: Apache Software License
Requires-Python: >=3.6
License-File: LICENSE
Requires-Dist: requests
Requires-Dist: click
